{
    "id": 0,
    "name": "C Template with Address Sanitizer",
    "version": "3",
    "languages": [
        "C"
    ],
    "tools": {
        "compile": {
            "require": "gcc",
            "features": [
                "optimize",
                "warn",
                "pedantic"
            ]
        },
        "compile[debug]": {
            "require": "gcc",
            "features": [
                "debug",
                "asan"
            ]
        },
        "execute": {
            "require": "asan"
        },
        "debug": [],
        "profile[asan]": {
            "require": "asan",
            "input_file": "stderr.txt",
            "fast": true
        }
    },
    "prepare": [
        "compile"
    ],
    "tests": [],
    "testTemplate": {
        "tools": [
            "compile[debug]",
            "execute",
            "debug",
            "profile[asan]"
        ]
    }
}
